{
  "headers": {
    "x-amz-cf-id": "KxXpURuwvlPUvZbZAsM3OWAGCoo7-1reQeYI8XRiHRZUkdetxPZ9tA==",
    "x-cache": "Hit from cloudfront",
    "vary": "Accept-Encoding",
    "accept-ranges": "bytes",
    "access-control-allow-origin": "*",
    "access-control-allow-methods": "GET",
    "content-security-policy": "default-src 'none'; style-src 'unsafe-inline'; sandbox",
    "x-amz-replication-status": "FAILED",
    "access-control-max-age": "0",
    "content-type": "application/typescript; charset=utf-8",
    "content-length": "23654",
    "etag": "\"e9ff8ee0683b3fdacb45ec4f54309cc1\"",
    "age": "12090469",
    "via": "http/2 edgeproxy-h",
    "cache-control": "public, max-age=31536000, immutable",
    "x-amz-cf-pop": "DFW56-P7",
    "x-amz-version-id": "oigQPs.eQat3Tru0srmSfRXR4R_t9GCn",
    "date": "Tue, 13 Sep 2022 16:21:50 GMT",
    "server": "deno/gcp-us-south1",
    "last-modified": "Wed, 24 Aug 2022 21:03:22 GMT"
  },
  "url": "https://deno.land/std@0.153.0/testing/asserts.ts",
  "now": {
    "secs_since_epoch": 1675176578,
    "nanos_since_epoch": 263254520
  }
}